<?xml version = '1.0' encoding = 'UTF-8'?>
<FKIndexAssociation class="oracle.dbtools.crest.model.design.relational.FKIndexAssociation" directorySegmentName="seg_3" id="60810AB4-BBF1-E0A1-387D-714E2EA236B0" containerWithKeyObject="CC3CF727-8406-F4DC-47DE-2F65F418526A" localFKIndex="43847717-0257-6137-5B7D-5C3D12E1816A" name="FK_LIQ20_TOT_LIQ_PER_01">
<sourceConnName>NUCMAYA</sourceConnName>
<sourceObjSchema>dbo</sourceObjSchema>
<sourceObjName>FK_LIQ20_TOT_LIQ_PER_01</sourceObjName>
<createdBy>MSosa</createdBy>
<createdTime>2023-06-16 22:40:56 UTC</createdTime>
<ownerDesignName>Base</ownerDesignName>
<referredTableLongName>BaseModelo_dbo.LIQ99_LIQUIDACION</referredTableLongName>
<deleteRule>NO ACTION</deleteRule>
<referredTableID>86163032-B59D-6A76-22C6-E352D9F345FC</referredTableID>
<keyObject>71E7B9F0-A16C-449E-EA79-2EFC68BD8F2A</keyObject>
<referredKeyID>71E7B9F0-A16C-449E-EA79-2EFC68BD8F2A</referredKeyID>
<mandatory>true</mandatory>
<refColNames>oi_liquidacion_ddo</refColNames>
<transferable>true</transferable>
<rely>false</rely>
<columnDependencyConstraintGenerateInDDL>true</columnDependencyConstraintGenerateInDDL>
</FKIndexAssociation>