<?xml version = '1.0' encoding = 'UTF-8'?>
<TableProxySqlServerv2k5 class="oracle.dbtools.crest.model.design.storage.sqlserver.v2k5.TableProxySqlServerv2k5" name="ORG52_SECTORES" directorySegmentName="seg_3" id="5BE8070B-F28C-6FC7-4498-62BC932FBC51">
<createdBy>MSosa</createdBy>
<createdTime>2023-06-16 22:36:50 UTC</createdTime>
<ownerDesignName>Base</ownerDesignName>
<schemaObject>7A030C0B-5C1E-5234-5B2D-6E045B94D5A8</schemaObject>
<database>484DB91B-7407-AE4E-7F51-8C1E74F61AC5</database>
<filegroup>EA555561-04A3-0896-CAB7-C0615D899657</filegroup>
<schema>1</schema>
<columnProxies>
<ColumnProxy class="oracle.dbtools.crest.model.design.storage.sqlserver.v2k12.ColumnProxySqlServerv2k12" name="c_sector" id="1593CD55-4093-4DCA-1BF6-606A3F1AA088">
<createdBy>MSosa</createdBy>
<createdTime>2023-06-16 22:36:50 UTC</createdTime>
<ownerDesignName>Base</ownerDesignName>
<collation>Modern_Spanish_CI_AS</collation>
</ColumnProxy>
<ColumnProxy class="oracle.dbtools.crest.model.design.storage.sqlserver.v2k12.ColumnProxySqlServerv2k12" name="oi_sector" id="4324E9BE-BA22-95CC-81BD-5E206D42E3AF">
<createdBy>MSosa</createdBy>
<createdTime>2023-06-16 22:36:50 UTC</createdTime>
<ownerDesignName>Base</ownerDesignName>
</ColumnProxy>
<ColumnProxy class="oracle.dbtools.crest.model.design.storage.sqlserver.v2k12.ColumnProxySqlServerv2k12" name="d_sector" id="925EAF02-1F68-A030-BAF8-D5B8732E179F">
<createdBy>MSosa</createdBy>
<createdTime>2023-06-16 22:36:50 UTC</createdTime>
<ownerDesignName>Base</ownerDesignName>
<collation>Modern_Spanish_CI_AS</collation>
</ColumnProxy>
<ColumnProxy class="oracle.dbtools.crest.model.design.storage.sqlserver.v2k12.ColumnProxySqlServerv2k12" name="oi_departamento" id="FF59DC92-98D5-C06A-87BC-F620E6AD2BE0">
<createdBy>MSosa</createdBy>
<createdTime>2023-06-16 22:36:50 UTC</createdTime>
<ownerDesignName>Base</ownerDesignName>
</ColumnProxy>
</columnProxies>
<foreignKeys>
<ForeignKey class="oracle.dbtools.crest.model.design.storage.sqlserver.v2k5.FKProxySqlServerv2k5" name="FK_ORG52_SECTORES_00" id="65506E2E-0BC0-C9F1-6ECB-9DABD6391418">
<createdBy>MSosa</createdBy>
<createdTime>2023-06-16 22:41:37 UTC</createdTime>
<ownerDesignName>Base</ownerDesignName>
</ForeignKey>
</foreignKeys>
<primaryKeys>
<PrimaryKey class="oracle.dbtools.crest.model.design.storage.sqlserver.v2k5.PKProxySqlServerv2k5" name="PK_ORG52_SECTORES" id="CB5C6AA4-5973-D1ED-EFFA-C99C05449671">
<createdBy>MSosa</createdBy>
<createdTime>2023-06-16 22:36:50 UTC</createdTime>
<ownerDesignName>Base</ownerDesignName>
<clustered>true</clustered>
<fileGroup>EA555561-04A3-0896-CAB7-C0615D899657</fileGroup>
<recomputeStatistics>NO</recomputeStatistics>
</PrimaryKey>
</primaryKeys>
<uniqueKeys>
<UniqueKey class="oracle.dbtools.crest.model.design.storage.sqlserver.v2k5.UniqueProxySqlServerv2k5" name="AK_ORG52_SECTORES_00" id="405E57C7-C850-5C49-AF1C-61440C5F3DB2">
<createdBy>MSosa</createdBy>
<createdTime>2023-06-16 22:36:51 UTC</createdTime>
<ownerDesignName>Base</ownerDesignName>
<fileGroup>EA555561-04A3-0896-CAB7-C0615D899657</fileGroup>
<recomputeStatistics>NO</recomputeStatistics>
</UniqueKey>
</uniqueKeys>
</TableProxySqlServerv2k5>