<form:Form xmlns:form="nomad_engine.form" name="NucleusRH.Base.Liquidacion.Interface.Variables.VariablesFijaPers_Ent.SeleccionArchivo.form" default_mode="EDIT">
	<form:Scripts/>
	<form:Title>
		<form:Label label="Interface de Datos Fijos por Legajos" style="S3 LCol_w" nowrap="1" name="lblTitulo"/>
	</form:Title>
	<form:Center>
		<form:Columns name="fgfg">
			<form:Column name="fgfgsaas">
				<form:Blank name="blank02"/>
				<form:Combo nvalue="#DATOSLIQ:@oi_empresa" action="COMBO" flow="NucleusRH.Base.Organizacion.Empresas.EMPRESA.Combo.autoflow" required="1" enabled="" label="Empresa" name="oi_empresa"/>
				<form:Blank name="blank03"/>
				<form:File nvalue="#DATOSLIQ:@file_name" class="INTERFACES" filename="IntVarLiqFij.dat" required="1" source="1" name="filArchivo" label="Archivo de interface">
					<form:SButtons>
						<form:SButton enabled="" visible="" name="sbHelper" label="Buscar un archivo." img="search">
							<form:Event runat="client" name="onclick" action="SHOW_HELPER"/>
						</form:SButton>
					</form:SButtons>
				</form:File>
				<form:Blank name="blank031"/>
				<form:Container rheight="400px" rwidth="700px" label="Aclaraciones" name="aa" borderwidth="1">
					<form:RowAligner name="dddd">
						<form:Row name="a1">
							<form:Label style="M1 LCol_t" name="formato" label="El formato del archivo es:"/>
							<form:Blank name="blank031"/>
						</form:Row>
						<form:Row name="a2">
							<form:Blank name="blank031"/>
							<form:Label name="formato1" label="NumeroLegajo;CodigoExternoVariable;Valor"/>
						</form:Row>
						<form:Row name="a3">
							<form:Label style="M1 LCol_t" name="validacion" label="Validaciones:"/>
							<form:Blank name="blank031"/>
						</form:Row>
						<form:Row name="a4">
							<form:Blank name="blank031"/>
							<form:Label name="validacion1" label="- La persona debe trabajar en la empresa"/>
						</form:Row>
						<form:Row name="a5">
							<form:Blank name="blank031"/>
							<form:Label name="validacion2" label="- El valor a ingresar debe tener el formato de la variable correspondiente"/>
						</form:Row>
						<form:Row name="a6">
							<form:Blank name="blank034"/>
							<form:Label name="validacion3" label="- La variable debe ser del tipo Datos Fijos del Empleado"/>
						</form:Row>
						<form:Row name="a61">
							<form:Blank name="blank0341"/>
							<form:Label name="validacion31" label="- Si hay dos registros para una misma persona con la misma variable, toma el ultimo valor"/>
						</form:Row>
						<form:Row name="a7">
							<form:Label style="M1 LCol_t" name="ejemplo" label="Ejemplo:"/>
							<form:Blank name="blank035"/>
						</form:Row>
						<form:Row name="a8">
							<form:Blank name="blank036"/>
							<form:Label name="ejemplo1" label="1;fp_hijos;5"/>
						</form:Row>
						<form:Row name="a9">
							<form:Blank name="blank037"/>
							<form:Label name="ejemplo2" label="2;fp_afiliado;0"/>
						</form:Row>
						<form:Row name="a11">
							<form:Blank name="blank038"/>
							<form:Label name="ejemplo3" label="161;fp_montoobrasocial;56.6"/>
						</form:Row>
						<form:Row name="a12">
							<form:Blank name="blank039"/>
							<form:Label name="ejemplo4" label="3;fp_conyuge;1"/>
						</form:Row>
					</form:RowAligner>
				</form:Container>
			</form:Column>
		</form:Columns>
	</form:Center>
	<form:Bottom>
		<form:RowAligner name="raBotonera">
			<form:Row name="row1">
				<form:Button label="Ejecutar" startvalidate="1" img="play" name="butEjecutar">
					<form:Event action="EJECUTAR" name="onclick" runat="server"/>
				</form:Button>
				<form:Button label="Volver" img="back" name="butVolver">
					<form:Event action="VOLVER" name="onclick" runat="server"/>
				</form:Button>
			</form:Row>
		</form:RowAligner>
	</form:Bottom>
</form:Form>
