<?xml version = '1.0' encoding = 'UTF-8'?>
<FKIndexAssociation class="oracle.dbtools.crest.model.design.relational.FKIndexAssociation" directorySegmentName="seg_13" id="AC36C6D9-A536-A719-6866-00890A7F30D5" containerWithKeyObject="6BF5E84C-2B22-844E-A9CE-29B1B96E8A76" localFKIndex="47EF9695-54E8-A978-6DE7-3B57C0ED8BA8" name="FK_TTA03_DETALLE_01">
<sourceConnName>NUCMAYA</sourceConnName>
<sourceObjSchema>dbo</sourceObjSchema>
<sourceObjName>FK_TTA03_DETALLE_01</sourceObjName>
<createdBy>MSosa</createdBy>
<createdTime>2023-06-16 22:40:02 UTC</createdTime>
<ownerDesignName>Base</ownerDesignName>
<referredTableLongName>BaseModelo_dbo.ORG02_ESTRUCTURAS</referredTableLongName>
<deleteRule>NO ACTION</deleteRule>
<referredTableID>5DA0C208-D783-766F-4D8B-781E6F028E58</referredTableID>
<keyObject>C755D43C-834E-FACE-A5CE-6114BE9C692F</keyObject>
<referredKeyID>C755D43C-834E-FACE-A5CE-6114BE9C692F</referredKeyID>
<mandatory>true</mandatory>
<refColNames>oi_estructura</refColNames>
<transferable>true</transferable>
<rely>false</rely>
<columnDependencyConstraintGenerateInDDL>true</columnDependencyConstraintGenerateInDDL>
</FKIndexAssociation>