<?xml version = '1.0' encoding = 'UTF-8'?>
<TableProxySqlServerv2k5 class="oracle.dbtools.crest.model.design.storage.sqlserver.v2k5.TableProxySqlServerv2k5" name="LIQ18_COL_FIJAS" directorySegmentName="seg_5" id="92F0CC80-3715-3206-CB3D-36411F81EC02">
<createdBy>MSosa</createdBy>
<createdTime>2023-06-16 22:29:53 UTC</createdTime>
<ownerDesignName>Base</ownerDesignName>
<schemaObject>7A030C0B-5C1E-5234-5B2D-6E045B94D5A8</schemaObject>
<database>484DB91B-7407-AE4E-7F51-8C1E74F61AC5</database>
<filegroup>EA555561-04A3-0896-CAB7-C0615D899657</filegroup>
<schema>1</schema>
<columnProxies>
<ColumnProxy class="oracle.dbtools.crest.model.design.storage.sqlserver.v2k12.ColumnProxySqlServerv2k12" name="c_tipo" id="028CFE7B-987F-9EF2-39E0-28D9624D2D5B">
<createdBy>MSosa</createdBy>
<createdTime>2023-06-16 22:29:53 UTC</createdTime>
<ownerDesignName>Base</ownerDesignName>
<collation>Modern_Spanish_CI_AS</collation>
</ColumnProxy>
<ColumnProxy class="oracle.dbtools.crest.model.design.storage.sqlserver.v2k12.ColumnProxySqlServerv2k12" name="o_style" id="09AEF808-FDD9-FDA8-25C1-98A971F82F8D">
<createdBy>MSosa</createdBy>
<createdTime>2023-06-16 22:29:53 UTC</createdTime>
<ownerDesignName>Base</ownerDesignName>
<collation>Modern_Spanish_CI_AS</collation>
</ColumnProxy>
<ColumnProxy class="oracle.dbtools.crest.model.design.storage.sqlserver.v2k12.ColumnProxySqlServerv2k12" name="e_posicion" id="558E37BA-6F7B-5CD0-D597-3E43D170951A">
<createdBy>MSosa</createdBy>
<createdTime>2023-06-16 22:29:53 UTC</createdTime>
<ownerDesignName>Base</ownerDesignName>
</ColumnProxy>
<ColumnProxy class="oracle.dbtools.crest.model.design.storage.sqlserver.v2k12.ColumnProxySqlServerv2k12" name="oi_columna_fija" id="98EA202E-A77A-12BA-8613-28756D366848">
<createdBy>MSosa</createdBy>
<createdTime>2023-06-16 22:29:53 UTC</createdTime>
<ownerDesignName>Base</ownerDesignName>
</ColumnProxy>
<ColumnProxy class="oracle.dbtools.crest.model.design.storage.sqlserver.v2k12.ColumnProxySqlServerv2k12" name="oi_reporte" id="A21B42E1-D1F8-4AD9-2D3A-FAD85A97B332">
<createdBy>MSosa</createdBy>
<createdTime>2023-06-16 22:29:53 UTC</createdTime>
<ownerDesignName>Base</ownerDesignName>
</ColumnProxy>
<ColumnProxy class="oracle.dbtools.crest.model.design.storage.sqlserver.v2k12.ColumnProxySqlServerv2k12" name="d_columna_fija" id="AD8B0142-106D-EA43-718A-DF4BF58A33D9">
<createdBy>MSosa</createdBy>
<createdTime>2023-06-16 22:29:53 UTC</createdTime>
<ownerDesignName>Base</ownerDesignName>
<collation>Modern_Spanish_CI_AS</collation>
</ColumnProxy>
<ColumnProxy class="oracle.dbtools.crest.model.design.storage.sqlserver.v2k12.ColumnProxySqlServerv2k12" name="c_columna_fija" id="D5EBEF74-08F4-80B8-16A5-C581E29AF5AD">
<createdBy>MSosa</createdBy>
<createdTime>2023-06-16 22:29:53 UTC</createdTime>
<ownerDesignName>Base</ownerDesignName>
<collation>Modern_Spanish_CI_AS</collation>
</ColumnProxy>
</columnProxies>
<foreignKeys>
<ForeignKey class="oracle.dbtools.crest.model.design.storage.sqlserver.v2k5.FKProxySqlServerv2k5" name="FK_LIQ18_COL_FIJAS_00" id="E550964E-6F28-5463-EF90-744CDBF35D96">
<createdBy>MSosa</createdBy>
<createdTime>2023-06-16 22:39:45 UTC</createdTime>
<ownerDesignName>Base</ownerDesignName>
</ForeignKey>
</foreignKeys>
<primaryKeys>
<PrimaryKey class="oracle.dbtools.crest.model.design.storage.sqlserver.v2k5.PKProxySqlServerv2k5" name="PK_LIQ18_COL_FIJAS" id="26AE3268-0D93-FFAD-7821-DCCB6E40149A">
<createdBy>MSosa</createdBy>
<createdTime>2023-06-16 22:29:54 UTC</createdTime>
<ownerDesignName>Base</ownerDesignName>
<clustered>true</clustered>
<fileGroup>EA555561-04A3-0896-CAB7-C0615D899657</fileGroup>
<recomputeStatistics>NO</recomputeStatistics>
</PrimaryKey>
</primaryKeys>
<uniqueKeys>
<UniqueKey class="oracle.dbtools.crest.model.design.storage.sqlserver.v2k5.UniqueProxySqlServerv2k5" name="AK_LIQ18_COL_FIJAS_00" id="37808AF1-6EDA-ECB1-F2E3-29D08293A85E">
<createdBy>MSosa</createdBy>
<createdTime>2023-06-16 22:29:54 UTC</createdTime>
<ownerDesignName>Base</ownerDesignName>
<fileGroup>EA555561-04A3-0896-CAB7-C0615D899657</fileGroup>
<recomputeStatistics>NO</recomputeStatistics>
</UniqueKey>
</uniqueKeys>
</TableProxySqlServerv2k5>