<html:html xmlns:html="nomad_engine.html" xmlns:qry="nomad_engine.qry" xmlns:xsl="http://www.w3.org/1999/XSL/Transform" name="Evaluacion Base" doc="source">
	<html:query declare="&lt;PARAMS oi_instance=&quot;407&quot; /&gt;" name="qry_report">
		<qry:main doc="SOURCE">
			<LOGS>
				<qry:attribute name="etty" value="$PROXY/@ETTY"/>
				<qry:attribute name="ut" value="$PROXY/@TOKEN"/>
				<qry:attribute name="mode" value="$SOURCE/PARAMS/@mode"/>
				<qry:attribute name="oi_instance" value="$SOURCE/PARAMS/@oi_instance"/>
				<qry:attribute name="oi_thread" value="0"/>
				<qry:attribute name="oi_node" value="0"/>
				<qry:insert-select name="LOAD_LOGS" doc-path="."/>
				<qry:insert-select name="TEST_THREAD" doc-path="."/>
			</LOGS>
		</qry:main>
		<qry:select doc="SOURCE" name="LOAD_LOGS">
			<qry:xquery>
				for $r in SQL('
select           
	L.oi_log,
	L.e_paso,
	L.c_tipo,
	L.f_accion,
	L.o_comentario
from
	WRK02_LOGS as L
where
	L.oi_instance={$SOURCE/@oi_instance}
order by
	e_paso ASC
			')/ROWS/ROW
			</qry:xquery>
			<qry:out>
				<LOG>
					<qry:attribute name="e_paso" value="$r/@e_paso"/>
					<qry:attribute name="c_tipo" value="$r/@c_tipo"/>
					<qry:attribute name="f_accion" value="format-date($r/@f_accion,'dd/mm/yyyy HH:MM:SS')"/>
					<qry:attribute name="o_comentario" value="$r/@o_comentario"/>
				</LOG>
			</qry:out>
		</qry:select>
		<qry:select doc="SOURCE" name="TEST_THREAD">
			<qry:xquery>
				for $r in SQL('
select           
	T.oi_thread,
	T.oi_node
from
	WRK02_THREADS as T
where       
  T.c_estado=\'WP\' and
	T.oi_instance={$SOURCE/@oi_instance}
			')/ROWS/ROW
			</qry:xquery>
			<qry:out>
				<qry:attribute name="oi_thread" value="$r/@oi_thread"/>
				<qry:attribute name="oi_node" value="$r/@oi_node"/>
			</qry:out>
		</qry:select>
	</html:query>
	<html:xslt>
		<xsl:template match="LOGS">
			<html>
				<head>
					<style media="screen">
						{
	background-color: #FFFFFF; 
	cursor: default;
	PADDING-RIGHT: 10px; 
	PADDING-LEFT: 10px; 
	PADDING-TOP: 10px; 
	PADDING-BOTTOM: 10px; 
	MARGIN: 0px; 
	BORDER-TOP-STYLE: none; 
	BORDER-RIGHT-STYLE: none; 
	BORDER-LEFT-STYLE: none; 
	BORDER-BOTTOM-STYLE: none; 
	background-image:url(Skins/_Default/Images/Workflow/CONSOLE/back.jpg);
}
.TABLE_PATH
{
	background-color: #FFFFFF;
	
	font-size: 9px;
	font-family: Verdana;
	color: #000000;          
	
	border:1px solid #A0A0A0;
	border-collapse:collapse;
	
	width:100%;
	
	cursor:default;
}
.TABLE_PATH_NORMAL
{
	background-color: #FFFFFF;
	
	font-size: 9px;
	font-family: Verdana;
	color: #000000;
	font-weight:normal;        
	
	text-align:left;
	
	cursor:default;
	padding-bottom:15px;
	
	padding-left:20px;
}
.TABLE_PATH_HIGH
{
	background-color: #FFFFFF;
	
	font-size: 12px;
	font-family: Verdana;
	color: #000000;
	font-weight:bold;
	background-image:url(Skins/_Default/Images/Workflow/CONSOLE/path_back.gif);
	
	text-align:left;
	padding-left:5px;
	padding-right:5px;
	
	cursor:pointer;
}
.TABLE_LOG
{
	background-color: #FFFFFF;
	
	font-size: 9px;
	font-family: Verdana;
	color: #000000;
	
	width:100%;
	border:1px solid #FFFFFF;
	border-collapse:collapse;
	
	cursor:default;
	
	table-layout:fixed;
}
.TABLE_LOG_TH
{
	background-color: #E0E0E0;
	
	font-size: 9px;
	font-family: Verdana;
	color: #000000;  
	font-weight:bold;
	
	background-image:url(Skins/_Default/Images/Workflow/CONSOLE/title_back.gif);
	
	text-align:left;
	border:1px solid #FFFFFF;
	padding-left:5px;
	padding-right:5px;
	
	cursor:default;
}
.TABLE_LOG_TD
{
	background-color: #F0F0F0;
	
	font-size: 9px;
	font-family: Verdana;
	color: #000000;  
	font-weight:normal;
	
	text-align:left;         
	border:1px solid #FFFFFF;
	padding-left:5px;
	padding-right:5px;
	
	cursor:default;
}
.TABLE_TASK_FOOT
{
	background-color: #E0E0E0;
	
	font-size: 9px;
	font-family: Verdana;
	color: #000000;  
	font-weight:bold;
	
	text-align:left;         
	border:1px solid #FFFFFF;
	padding-left:5px;
	padding-right:5px;
	
	cursor:default;
}
.TABLE_TASK_ERROR
{
	background-color: #F0F0F0;
	
	font-size: 9px;
	font-family: Verdana;
	color: #C05050;  
	font-weight:bold;
	
	text-align:left;         
	border:1px solid #FFFFFF;
	padding-left:5px;
	padding-right:5px;
	
	cursor:default;
}
.TABLE_LINK
{
	background-color: #FFFFFF;
	
	font-size: 9px;
	font-family: Verdana;
	color: #000000;
	
	width:100%;
	border-collapse:collapse;
	
	cursor:default;
	table-layout:fixed;
}
.TABLE_LINK_TD
{
	font-size: 9px;
	font-family: Verdana;
	color: #000000;  
	font-weight:normal;
	
	text-align:left;         
	padding-left:5px;
	
	cursor:pointer;
}
.TABLE_LINK_ERROR
{
	font-size: 9px;
	font-family: Verdana;
	color: #C05050;  
	font-weight:bold;
	
	text-align:left;         
	padding-left:5px;
	
	cursor:default;
}
					</style>
					<script>
						function amp()
{
	return String.fromCharCode(38);
}

function SetHTML(txt)
{
	var obj;
	var aux;
	
	//Arreglo el Titulo
	obj=document.getElementById("table_log");
	obj.innerHTML=txt;        
}

function AutoRefresh() 
{ 
	var oi_instance=document.getElementById("AUX_IFRAME").getAttribute("nmd-instance");
	var ut         =document.getElementById("AUX_IFRAME").getAttribute("nmd-ut");
    
    var crc = parent.CRC32("PARAMS:file=NucleusWF.Base.Ejecucion.WaitProcess.rpt|oi_instance="+oi_instance+"|mode=refresh");    

	document.getElementById("AUX_IFRAME").src="ReportViewer.aspx?ut="+ut+amp()+"file=NucleusWF.Base.Ejecucion.WaitProcess.rpt"+amp()+"oi_instance="+oi_instance+amp()+"mode=refresh"+amp()+"crc="+crc;
	window.setTimeout("AutoRefresh();",3000);
}

/*function AutoRefresh() 
{ 
	var oi_instance=document.getElementById("AUX_IFRAME").getAttribute("nmd-instance");
	var ut         =document.getElementById("AUX_IFRAME").getAttribute("nmd-ut");
    
    var crc = parent.CRC32("PARAMS:file=NucleusWF.Base.Ejecucion.WaitProcess.rpt|oi_instance="+oi_instance+"|mode=refresh");    

	document.getElementById("AUX_IFRAME").src="ReportViewer.aspx?ut="+ut+amp()+"file=NucleusWF.Base.Ejecucion.WaitProcess.rpt"+amp()+"oi_instance="+oi_instance+amp()+"mode=refresh"+amp()+"crc="+crc;
	window.setTimeout("AutoRefresh();",3000);
} */
                  
function FinishWait(oi_thread, oi_node) 
{ 
	parent.FinishWait(oi_thread, oi_node);
}

function HTMLOnLoad()
{
	var mode     =document.getElementById("AUX_IFRAME").getAttribute("nmd-mode");
	var oi_thread=document.getElementById("AUX_IFRAME").getAttribute("nmd-thread");
	var oi_node  =document.getElementById("AUX_IFRAME").getAttribute("nmd-node");
	
	if (oi_thread!="0") 
		parent.FinishWait(oi_thread, oi_node);
	else
	if (mode=="") 
		window.setTimeout("AutoRefresh();",2000);
	else 
		parent.SetHTML(""+document.getElementById("table_log").innerHTML);
}
					</script>
				</head>
				<body onload="HTMLOnLoad();" scroll="no">
					<div id="table_log" name="table_log">
						<table CELLPADDING="0" CELLSPACING="0" class="TABLE_LOG" border="1">
							<col width="30px"/>
							<col width="100px"/>
							<col/>
							<tr height="20px">
								<th class="TABLE_LOG_TH">
									Tipo
								</th>
								<th class="TABLE_LOG_TH" style="text-align:center;">
									Fecha Hora
								</th>
								<th class="TABLE_LOG_TH" style="text-align:center;">
									Mensaje
								</th>
							</tr>
							<xsl:for-each select="LOG">
								<tr>
									<td class="TABLE_LOG_TD" align="center">
										<xsl:choose>
											<xsl:when test="@c_tipo='IFO'">
												<img src="Skins/_Default/Images/Workflow/Logs/IFO.gif"/>
											</xsl:when>
											<xsl:when test="@c_tipo='WRN'">
												<img src="Skins/_Default/Images/Workflow/Logs/WRN.gif"/>
											</xsl:when>
											<xsl:when test="@c_tipo='ERR'">
												<img src="Skins/_Default/Images/Workflow/Logs/ERR.gif"/>
											</xsl:when>
											<xsl:when test="@c_tipo='EXE'">
												<img src="Skins/_Default/Images/Workflow/Logs/EXE.gif"/>
											</xsl:when>
										</xsl:choose>
									</td>
									<td class="TABLE_LOG_TD" style="text-align:center;">
										<xsl:value-of select="@f_accion"/>
									</td>
									<td class="TABLE_LOG_TD">
										<xsl:value-of select="@o_comentario"/>
									</td>
								</tr>
							</xsl:for-each>
						</table>
					</div>
					<iframe id="AUX_IFRAME" name="AUX_IFRAME" src="about:blank" style="display:none;">
						<xsl:attribute name="nmd-mode">
							<xsl:value-of select="@mode"/>
						</xsl:attribute>
						<xsl:attribute name="nmd-ut">
							<xsl:value-of select="@ut"/>
						</xsl:attribute>
						<xsl:attribute name="nmd-thread">
							<xsl:value-of select="@oi_thread"/>
						</xsl:attribute>
						<xsl:attribute name="nmd-node">
							<xsl:value-of select="@oi_node"/>
						</xsl:attribute>
						<xsl:attribute name="nmd-instance">
							<xsl:value-of select="@oi_instance"/>
						</xsl:attribute>
						.
					</iframe>
				</body>
			</html>
		</xsl:template>
	</html:xslt>
</html:html>
