<?xml version = '1.0' encoding = 'UTF-8'?>
<FKIndexAssociation class="oracle.dbtools.crest.model.design.relational.FKIndexAssociation" directorySegmentName="seg_1" id="E2BDE373-E8B5-17D8-E4E9-9913F4466004" containerWithKeyObject="F6B80BD0-AD22-66E8-AEAA-3A65716E5D7F" localFKIndex="94F4C6F0-DF49-4EEB-23A6-FEB07D16156F" name="FK_CYD17_TERCEROS_00">
<sourceConnName>NUCMAYA</sourceConnName>
<sourceObjSchema>dbo</sourceObjSchema>
<sourceObjName>FK_CYD17_TERCEROS_00</sourceObjName>
<createdBy>MSosa</createdBy>
<createdTime>2023-06-16 22:39:52 UTC</createdTime>
<ownerDesignName>Base</ownerDesignName>
<referredTableLongName>BaseModelo_dbo.PER20_TIPOS_DOC</referredTableLongName>
<deleteRule>NO ACTION</deleteRule>
<referredTableID>AEC848C8-AD92-8477-54D5-040796A02A6B</referredTableID>
<keyObject>2A64C6D2-F60B-3F57-2912-394763304A07</keyObject>
<referredKeyID>2A64C6D2-F60B-3F57-2912-394763304A07</referredKeyID>
<mandatory>true</mandatory>
<refColNames>oi_tipo_documento</refColNames>
<transferable>true</transferable>
<rely>false</rely>
<columnDependencyConstraintGenerateInDDL>true</columnDependencyConstraintGenerateInDDL>
</FKIndexAssociation>